prodmodel/__init__.py
prodmodel/__main__.py
prodmodel/docgen.py
prodmodel/executor.py
prodmodel/file_cache.py
prodmodel/globals.py
prodmodel/main.py
prodmodel/rules.py
prodmodel/setup.py
prodmodel/util.py
prodmodel/ee/__init__.py
prodmodel/ee/aws_rules.py
prodmodel/ee/model/__init__.py
prodmodel/ee/model/s3_data_target.py
prodmodel/model/__init__.py
prodmodel/model/artifact.py
prodmodel/model/csv_data_target.py
prodmodel/model/data_file.py
prodmodel/model/data_target.py
prodmodel/model/encode_label_data_target.py
prodmodel/model/external_data_artifact.py
prodmodel/model/external_data_file.py
prodmodel/model/external_data_target.py
prodmodel/model/file_cache.py
prodmodel/model/input_file.py
prodmodel/model/iterable_data_target.py
prodmodel/model/label_encoder_target.py
prodmodel/model/pickle_data_target.py
prodmodel/model/py_file.py
prodmodel/model/s3_data_target.py
prodmodel/model/sample_data_target.py
prodmodel/model/select_data_target.py
prodmodel/model/target.py
prodmodel/model/test_target.py
prodmodel/model/transform_data_target.py
prodmodel/model/transform_stream_data_target.py
prodmodel/model/files/__init__.py
prodmodel/model/files/data_file.py
prodmodel/model/files/external_data_file.py
prodmodel/model/files/file_util.py
prodmodel/model/files/input_file.py
prodmodel/model/files/py_file.py
prodmodel/model/files/s3_data_file.py
prodmodel/model/files/shape_file_util.py
prodmodel/model/target/__init__.py
prodmodel/model/target/binary_data_target.py
prodmodel/model/target/csv_data_target.py
prodmodel/model/target/data_target.py
prodmodel/model/target/deploy_target.py
prodmodel/model/target/encode_label_data_target.py
prodmodel/model/target/external_data_target.py
prodmodel/model/target/iterable_data_target.py
prodmodel/model/target/json_data_target.py
prodmodel/model/target/label_encoder_target.py
prodmodel/model/target/pickle_data_target.py
prodmodel/model/target/s3_data_target.py
prodmodel/model/target/sample_data_target.py
prodmodel-0.4.3.dist-info/LICENCE
prodmodel-0.4.3.dist-info/METADATA
prodmodel-0.4.3.dist-info/WHEEL
prodmodel-0.4.3.dist-info/entry_points.txt
prodmodel-0.4.3.dist-info/top_level.txt
prodmodel-0.4.3.dist-info/RECORD
