Metadata-Version: 2.1
Name: prodmodel
Version: 0.4.3
Summary: Build data science pipelines and models
Home-page: https://github.com/prodmodel/prodmodel
Author: Gergely Svigruha
Author-email: gergely.svigruha@prodmodel.com
License: UNKNOWN
Platform: UNKNOWN
Classifier: Programming Language :: Python :: 3.5
Classifier: Programming Language :: Python :: 3.6
Classifier: Programming Language :: Python :: 3.7
Classifier: License :: OSI Approved :: Apache Software License
Classifier: Operating System :: OS Independent
Classifier: Development Status :: 4 - Beta
